robot_tools/__init__.py
robot_tools/base_control.py
robot_tools/biner.py
robot_tools/caner.py
robot_tools/conversions.py
robot_tools/coordinate.py
robot_tools/datar.py
robot_tools/interpolate.py
robot_tools/modeler.py
robot_tools/multi_tp.py
robot_tools/painter.py
robot_tools/pather.py
robot_tools/performancer.py
robot_tools/recorder.py
robot_tools/roser.py
robot_tools/trajer.py
robot_tools/transformations.py
robotics_tools-1.0.2.dist-info/LICENSE
robotics_tools-1.0.2.dist-info/METADATA
robotics_tools-1.0.2.dist-info/WHEEL
robotics_tools-1.0.2.dist-info/top_level.txt
robotics_tools-1.0.2.dist-info/RECORD
